cspark/cli/__init__.py
cspark/cli/_main.py
cspark/cli/_utils.py
cspark/cli/_commands/__init__.py
cspark/cli/_commands/_api.py
cspark/cli/_commands/_auth.py
cspark/cli/_commands/_config.py
cspark/cli/_commands/_folders.py
cspark/cli/_commands/_services.py
cspark/cli/_commands/_versions.py
cspark/sdk/__init__.py
cspark/sdk/_auth.py
cspark/sdk/_client.py
cspark/sdk/_config.py
cspark/sdk/_constants.py
cspark/sdk/_errors.py
cspark/sdk/_logger.py
cspark/sdk/_utils.py
cspark/sdk/_validators.py
cspark/sdk/_version.py
cspark/sdk/resources/__init__.py
cspark/sdk/resources/_base.py
cspark/sdk/resources/_batches.py
cspark/sdk/resources/_folders.py
cspark/sdk/resources/_health.py
cspark/sdk/resources/_history.py
cspark/sdk/resources/_impex.py
cspark/sdk/resources/_oauth2.py
cspark/sdk/resources/_services.py
cspark/sdk/resources/_transforms.py
cspark/wasm/__init__.py
cspark/wasm/_client.py
cspark/wasm/_config.py
cspark/wasm/_constants.py
cspark/wasm/_version.py
cspark/wasm/resources/__init__.py
cspark/wasm/resources/_base.py
cspark/wasm/resources/_services.py
cspark-0.2.3.dist-info/METADATA
cspark-0.2.3.dist-info/WHEEL
cspark-0.2.3.dist-info/entry_points.txt
cspark-0.2.3.dist-info/licenses/LICENSE
cspark-0.2.3.dist-info/RECORD
