Metadata-Version: 2.4
Name: cspark
Version: 0.2.3
Summary: A Python SDK for interacting with Coherent Spark APIs
Project-URL: Repository, https://github.com/Coherent-Partners/spark-python-sdk
Project-URL: Homepage, https://github.com/Coherent-Partners/spark-python-sdk/blob/main/docs/readme.md
Project-URL: Changelog, https://github.com/Coherent-Partners/spark-python-sdk/blob/main/CHANGELOG.md
Author-email: Coherent <team@coherent.global>
License-Expression: Apache-2.0
License-File: LICENSE
Keywords: api,coherent,restful,sdk,spark
Classifier: Intended Audience :: Developers
Classifier: License :: OSI Approved :: Apache Software License
Classifier: Operating System :: MacOS
Classifier: Operating System :: Microsoft :: Windows
Classifier: Operating System :: OS Independent
Classifier: Operating System :: POSIX
Classifier: Operating System :: POSIX :: Linux
Classifier: Programming Language :: Python :: 3.7
Classifier: Programming Language :: Python :: 3.8
Classifier: Programming Language :: Python :: 3.9
Classifier: Programming Language :: Python :: 3.10
Classifier: Programming Language :: Python :: 3.11
Classifier: Programming Language :: Python :: 3.12
Classifier: Topic :: Software Development :: Libraries :: Python Modules
Classifier: Typing :: Typed
Requires-Python: >=3.7
Requires-Dist: dataclasses
Requires-Dist: httpx<1,>=0.23.0
Provides-Extra: cli
Requires-Dist: click==8.*; extra == 'cli'
Requires-Dist: inquirerpy==0.3.*; extra == 'cli'
Requires-Dist: pyyaml>=6.0.0; extra == 'cli'
Requires-Dist: rich>=10; extra == 'cli'
